Metadata-Version: 2.1
Name: mediamaker
Version: 0.3.0
Summary: Media Maker Python SDK for Blue Brain BioExplorer
Home-page: https://github.com/BlueBrain/BioExplorer.git
Author: Blue Brain Project, EPFL
Author-email: bbp-open-source@googlegroups.com
License: GNU GPL
Project-URL: Documentation, https://bluebrain.github.io/BioExplorer/
Project-URL: Source, https://github.com/BlueBrain/BioExplorer
Keywords: covid,covid19,coronavirus,bbp,blue,brain,virus,molecule,molecular system
Platform: UNKNOWN
Classifier: Development Status :: 4 - Beta
Classifier: License :: OSI Approved :: GNU Lesser General Public License v3 (LGPLv3)
Classifier: Operating System :: OS Independent
Classifier: Programming Language :: Python :: 3.6
Classifier: Programming Language :: Python :: 3.7
Classifier: Topic :: Software Development :: Libraries
Classifier: Topic :: Software Development :: Libraries :: Python Modules
